LONG_DESCRIPTION.rst
MANIFEST.in
setup.py
reactor/__init__.py
reactor/common.py
reactor.egg-info/PKG-INFO
reactor.egg-info/SOURCES.txt
reactor.egg-info/dependency_links.txt
reactor.egg-info/requires.txt
reactor.egg-info/top_level.txt
test/test_common.py