Metadata-Version: 1.1
Name: reactor
Version: 0.1.4
Summary: Reactor.am python client
Home-page: https://reactor.am/
Author: Reactor
Author-email: hello@reactor.am
License: UNKNOWN
Platform: UNKNOWN
Classifier: Development Status :: 5 - Production/Stable
Classifier: Intended Audience :: Customer Service
Classifier: License :: OSI Approved :: GNU General Public License v2 (GPLv2)
Classifier: Programming Language :: Python :: 2.7
